README.md
setup.cfg
setup.py
stone_burner/__init__.py
stone_burner/cli.py
stone_burner/config.py
stone_burner/install.py
stone_burner/lib.py
stone_burner/options.py
stone_burner/utils.py
stone_burner.egg-info/PKG-INFO
stone_burner.egg-info/SOURCES.txt
stone_burner.egg-info/dependency_links.txt
stone_burner.egg-info/entry_points.txt
stone_burner.egg-info/requires.txt
stone_burner.egg-info/top_level.txt
tests/__init__.py
tests/test_config.py
tests/test_install.py
tests/test_lib.py
tests/test_options.py
tests/utils.py