Metadata-Version: 1.1
Name: stone-burner
Version: 0.11.0
Summary: Give more power to Terraform.
Home-page: https://github.com/kkvesper/stone-burner
Author: Rodrigo Argüello Flores
Author-email: rodrigo@kkvesper.jp
License: UNKNOWN
Download-URL: https://github.com/kkvesper/stone-burner/archive/v0.11.0.tar.gz
Keywords: terraform,planetary-annihilation,infrastructure-as-code
Platform: UNKNOWN
